rsa_api/__init__.py
rsa_api/rsa_api.py
tekrsa_api_wrap-2.0.1.dist-info/METADATA
tekrsa_api_wrap-2.0.1.dist-info/WHEEL
tekrsa_api_wrap-2.0.1.dist-info/licenses/LICENSE.md
tekrsa_api_wrap-2.0.1.dist-info/RECORD
