Metadata-Version: 2.4
Name: tekrsa-api-wrap
Version: 2.0.1
Summary: NTIA/ITS Python wrapper for the Tektronix RSA API for Linux
Project-URL: Repository, https://github.com/NTIA/tekrsa-api-wrap
Project-URL: Bug Tracker, https://github.com/NTIA/tekrsa-api-wrap/issues
Project-URL: NTIA GitHub, https://github.com/NTIA
Project-URL: ITS Website, https://its.ntia.gov
Project-URL: Tektronix Website, https://www.tek.com/en
Author: The Institute for Telecommunication Sciences
License: # SOFTWARE DISCLAIMER / RELEASE
License-File: LICENSE.md
Keywords: API,Linux,RF,RSA,SCOS,SDR,Tektronix,analyzer,radio,spectrum,wrapper
Classifier: Intended Audience :: Developers
Classifier: Intended Audience :: Science/Research
Classifier: Intended Audience :: Telecommunications Industry
Classifier: Natural Language :: English
Classifier: Operating System :: POSIX :: Linux
Classifier: Programming Language :: Python
Classifier: Programming Language :: Python :: 3
Classifier: Programming Language :: Python :: 3.9
Classifier: Programming Language :: Python :: 3.10
Classifier: Programming Language :: Python :: 3.11
Classifier: Programming Language :: Python :: 3.12
Classifier: Programming Language :: Python :: 3.13
Requires-Python: >=3.9
Requires-Dist: numpy>=1.25
Provides-Extra: dev
Requires-Dist: hatchling<2.0,>=1.6.0; extra == 'dev'
Requires-Dist: pre-commit<5.0,>=4.0; extra == 'dev'
Requires-Dist: twine<6.0,>=5.0; extra == 'dev'
